ducknotify/__init__.py
ducknotify-1.0.0.dist-info/LICENSE
ducknotify-1.0.0.dist-info/METADATA
ducknotify-1.0.0.dist-info/WHEEL
ducknotify-1.0.0.dist-info/top_level.txt
ducknotify-1.0.0.dist-info/RECORD
