Metadata-Version: 2.1
Name: ducknotify
Version: 1.0.0
Summary: **DuckNotify** is a lightweight, cross-platform Python library for sending desktop notifications effortlessly. It works on **Windows**, **macOS**, and **Linux**, providing a simple API to notify users with custom messages.
Home-page: https://github.com/freeutka/DuckNotify
Author: freeutka
Author-email: freeutka@inbox.lv
Classifier: Programming Language :: Python :: 3
Classifier: License :: OSI Approved :: MIT License
Classifier: Operating System :: OS Independent
Requires-Python: >=3.6
License-File: LICENSE
Requires-Dist: osascript
Requires-Dist: notify-send
Requires-Dist: plyer
